my_opentelemetry_setup/__init__.py
my_opentelemetry_setup-0.1.0.dist-info/METADATA
my_opentelemetry_setup-0.1.0.dist-info/WHEEL
my_opentelemetry_setup-0.1.0.dist-info/top_level.txt
my_opentelemetry_setup-0.1.0.dist-info/RECORD
