Metadata-Version: 2.1
Name: my-opentelemetry-setup
Version: 0.1.0
Summary: A package to setup OpenTelemetry for LangChain projects
Home-page: https://github.com/eliazulai29/my_opentelemetry_setup.git
Author: 
Author-email: 
Classifier: Programming Language :: Python :: 3
Classifier: License :: OSI Approved :: MIT License
Classifier: Operating System :: OS Independent
Requires-Python: >=3.6
Requires-Dist: opentelemetry-api
Requires-Dist: opentelemetry-sdk
Requires-Dist: opentelemetry-exporter-otlp-proto-grpc
Requires-Dist: phoenix-trace-langchain
